xl2sitemap/__init__.py
xl2sitemap/__main__.py
xl2sitemap/xl2sitemap.py
xl2sitemap-0.1.3.dist-info/LICENSE
xl2sitemap-0.1.3.dist-info/METADATA
xl2sitemap-0.1.3.dist-info/WHEEL
xl2sitemap-0.1.3.dist-info/entry_points.txt
xl2sitemap-0.1.3.dist-info/top_level.txt
xl2sitemap-0.1.3.dist-info/RECORD
