Metadata-Version: 2.1
Name: xl2sitemap
Version: 0.1.3
Summary: Generate heavy sitemap files using excel sheets
Home-page: https://github.com/antiproblemist/excel-to-sitemap
Author: Shahzeb Qureshi
Author-email: shahzeb_iam@outlook.com
License: UNKNOWN
Platform: UNKNOWN
Classifier: Environment :: Console
Classifier: Intended Audience :: Developers
Classifier: Topic :: Software Development
Requires-Dist: pandas (>=0.24.2)
Requires-Dist: tqdm (>=4.32.1)
Requires-Dist: numpy (>=1.16.3)
Requires-Dist: xlrd (>=1.2.0)
